FAST/__init__.py
FAST/motility.py
FAST/plotparams.py
FASTrack-1.0.0.data/scripts/fast
FASTrack-1.0.0.data/scripts/lima
FASTrack-1.0.0.data/scripts/ppss
FASTrack-1.0.0.data/scripts/stack2tifs
FASTrack-1.0.0.dist-info/LICENSE
FASTrack-1.0.0.dist-info/METADATA
FASTrack-1.0.0.dist-info/WHEEL
FASTrack-1.0.0.dist-info/top_level.txt
FASTrack-1.0.0.dist-info/RECORD
