Metadata-Version: 2.1
Name: FASTrack
Version: 1.0.0
Summary: Automated filament tracker for in-vitro motility actin gliding assays
Home-page: https://github.com/turalaksel/FAST
Author: Tural Aksel
Author-email: turalaksel@gmail.com
License: UNKNOWN
Platform: UNKNOWN
Classifier: Programming Language :: Python :: 3
Classifier: License :: OSI Approved :: MIT License
Classifier: Operating System :: OS Independent
Requires-Python: >=2.7, !=3.*
Requires-Dist: backports.functools-lru-cache (==1.5)
Requires-Dist: cycler (==0.10.0)
Requires-Dist: decorator (==4.3.0)
Requires-Dist: enum34 (==1.1.6)
Requires-Dist: futures (==3.2.0)
Requires-Dist: imageio (==2.3.0)
Requires-Dist: kiwisolver (==1.0.1)
Requires-Dist: matplotlib (==2.2.2)
Requires-Dist: networkx (==2.1)
Requires-Dist: numpy (==1.11.2)
Requires-Dist: opencv-python (==3.4.0.12)
Requires-Dist: Pillow (==5.1.0)
Requires-Dist: pyparsing (==2.2.0)
Requires-Dist: python-dateutil (==2.7.2)
Requires-Dist: pytz (==2018.4)
Requires-Dist: PyWavelets (==0.5.2)
Requires-Dist: scikit-image (==0.13.1)
Requires-Dist: scipy (==1.0.1)
Requires-Dist: six (==1.11.0)
Requires-Dist: subprocess32 (==3.2.7)
